pandas_survey_toolkit/__init__.py
pandas_survey_toolkit/analytics.py
pandas_survey_toolkit/nlp.py
pandas_survey_toolkit/utils.py
pandas_survey_toolkit/vis.py
pandas_survey_toolkit-1.0.13.dist-info/licenses/LICENSE
pandas_survey_toolkit-1.0.13.dist-info/METADATA
pandas_survey_toolkit-1.0.13.dist-info/WHEEL
pandas_survey_toolkit-1.0.13.dist-info/top_level.txt
pandas_survey_toolkit-1.0.13.dist-info/RECORD
