Metadata-Version: 2.4
Name: pandas-survey-toolkit
Version: 1.0.13
Summary: A pandas extension for survey analysis
Home-page: https://github.com/Andy7475/pandas-survey-toolkit
Author: Andy Laing
Author-email: andylaing5@gmail.com
License: MIT
Project-URL: Bug Tracker, https://github.com/Andy7475/pandas-survey-toolkit/issues
Classifier: Programming Language :: Python :: 3
Classifier: License :: OSI Approved :: MIT License
Classifier: Operating System :: OS Independent
Requires-Python: >=3.9,<=3.12
License-File: LICENSE
Requires-Dist: torch<3.0,>=2.1.0
Requires-Dist: sentence-transformers<4.0,>=3.0
Requires-Dist: umap-learn<1.0,>=0.5
Requires-Dist: scikit-learn<2.0,>=1.3
Requires-Dist: pandas<3.0,>=2.2.0
Requires-Dist: numpy<2.0,>=1.26.0
Requires-Dist: pandas-flavor<1.0,>=0.6.0
Requires-Dist: spacy<4.0,>=3.0.0
Requires-Dist: gensim<5.0,>=4.3.3
Requires-Dist: scipy<1.15.0,>=1.10.0
Requires-Dist: altair<5.0,>=4.0.0
Requires-Dist: matplotlib<4.0,>=3.0.0
Requires-Dist: pyvis<1.0,>=0.3.2
Requires-Dist: transformers<5.0,>=4.20.0
Dynamic: author
Dynamic: author-email
Dynamic: classifier
Dynamic: description
Dynamic: description-content-type
Dynamic: home-page
Dynamic: license
Dynamic: license-file
Dynamic: project-url
Dynamic: requires-dist
Dynamic: requires-python
Dynamic: summary
